pycanoe/__init__.py
patm-0.1.dist-info/METADATA
patm-0.1.dist-info/WHEEL
patm-0.1.dist-info/top_level.txt
patm-0.1.dist-info/RECORD
