Metadata-Version: 2.1
Name: patm
Version: 0.1
Summary: Comprehensive Atmosphere N' Ocean Engine
Home-page: https://github.com/chengcli/canoe
Author: Cheng Li
Author-email: chengcli@umich.edu
License: MIT
Platform: UNKNOWN
Classifier: Programming Language :: Python :: 3
Classifier: License :: OSI Approved :: MIT License
Classifier: Operating System :: OS Independent
